{"task_id": "rf-146065", "max_evals": 50, "batch_size": 5, "n_repeat": 3, "experiments": [[{"n_estimators": 1512, "min_samples_leaf": 1, "max_features": 0.8, "max_depth": 8, "bootstrap": false, "score": 0.9983333333333334, "surrogate": 0.9983333333333334}, {"bootstrap": 0, "max_depth": 14, "max_features": 0.8, "min_samples_leaf": 4, "n_estimators": 1979, "score": 0.9825641025641026, "surrogate": 0.1875505952909828}, {"bootstrap": 1, "max_depth": 2, "max_features": 0.8, "min_samples_leaf": 1, "n_estimators": 3, "score": 0.5653571428571429, "surrogate": 0.14081498891446742}, {"bootstrap": 0, "max_depth": 1, "max_features": "log2", "min_samples_leaf": 1, "n_estimators": 35, "score": 0.5497588522588522, "surrogate": 0.0005304225295943326}, {"bootstrap": 0, "max_depth": 1, "max_features": "sqrt", "min_samples_leaf": 1, "n_estimators": 25, "score": 0.555862332112332, "surrogate": 0.00706495286586744}, {"bootstrap": 0, "max_depth": 15, "max_features": 0.5, "min_samples_leaf": 1, "n_estimators": 1739, "score": 0.9977380952380953, "surrogate": 0.0070613312948233364}, {"bootstrap": 0, "max_depth": 13, "max_features": 0.9, "min_samples_leaf": 1, "n_estimators": 11, "score": 0.9954304029304029, "surrogate": 0.006259175823229768}, {"bootstrap": 0, "max_depth": 1, "max_features": 0.1, "min_samples_leaf": 1, "n_estimators": 1853, "score": 0.5563736263736263, "surrogate": 0.0062241058797578575}, {"bootstrap": 0, "max_depth": 1, "max_features": 0.6, "min_samples_leaf": 1, "n_estimators": 1973, "score": 0.5352777777777777, "surrogate": 0.005198870874178245}, {"bootstrap": 0, "max_depth": 1, "max_features": 0.7, "min_samples_leaf": 1, "n_estimators": 1795, "score": 0.5340155677655678, "surrogate": 0.004242610857313528}, {"bootstrap": 0, "max_depth": 1, "max_features": 0.4, "min_samples_leaf": 1, "n_estimators": 1604, "score": 0.549029304029304, "surrogate": 0.0032740581728644812}, {"bootstrap": 0, "max_depth": 19, "max_features": 1.0, "min_samples_leaf": 1, "n_estimators": 92, "score": 0.9672115384615385, "surrogate": 0.009448276792603849}, {"bootstrap": 0, "max_depth": 1, "max_features": 0.3, "min_samples_leaf": 1, "n_estimators": 1678, "score": 0.5574267399267401, "surrogate": 0.002279789756702455}, {"bootstrap": 1, "max_depth": 13, "max_features": 0.2, "min_samples_leaf": 5, "n_estimators": 4, "score": 0.7548840048840051, "surrogate": 0.010324230541490675}, {"bootstrap": 0, "max_depth": 1, "max_features": 0.2, "min_samples_leaf": 1, "n_estimators": 1766, "score": 0.5540262515262515, "surrogate": 1.1387938926901287}, {"bootstrap": 1, "max_depth": 16, "max_features": 0.6, "min_samples_leaf": 4, "n_estimators": 670, "score": 0.9226800976800977, "surrogate": 0.0}, {"bootstrap": 1, "max_depth": 19, "max_features": 0.8, "min_samples_leaf": 9, "n_estimators": 1972, "score": 0.8407142857142856, "surrogate": 0.5875578040055416}, {"bootstrap": 1, "max_depth": 8, "max_features": 0.1, "min_samples_leaf": 4, "n_estimators": 1994, "score": 0.8932509157509158, "surrogate": 0.8932365485412976}, {"bootstrap": 1, "max_depth": 16, "max_features": 0.7, "min_samples_leaf": 7, "n_estimators": 1999, "score": 0.8711233211233212, "surrogate": 0.7793658907560888}, {"bootstrap": 1, "max_depth": 1, "max_features": 0.7, "min_samples_leaf": 4, "n_estimators": 1975, "score": 0.544047619047619, "surrogate": 0.8338754359146039}, {"bootstrap": 1, "max_depth": 9, "max_features": 1.0, "min_samples_leaf": 3, "n_estimators": 1971, "score": 0.9647619047619049, "surrogate": 1.1023885630647783}, {"bootstrap": 1, "max_depth": 12, "max_features": 0.9, "min_samples_leaf": 4, "n_estimators": 1883, "score": 0.9388186813186813, "surrogate": 1.0920051307943517}, {"bootstrap": 0, "max_depth": 19, "max_features": 0.2, "min_samples_leaf": 1, "n_estimators": 1593, "score": 0.9794871794871796, "surrogate": 0.8022648617847219}, {"bootstrap": 0, "max_depth": 1, "max_features": 0.9, "min_samples_leaf": 9, "n_estimators": 24, "score": 0.5025442612942614, "surrogate": 0.6264883063444024}, {"bootstrap": 0, "max_depth": 8, "max_features": 0.2, "min_samples_leaf": 1, "n_estimators": 1973, "score": 0.9820268620268621, "surrogate": 0.7869455596331036}, {"bootstrap": 0, "max_depth": 19, "max_features": 0.9, "min_samples_leaf": 6, "n_estimators": 873, "score": 0.9463064713064713, "surrogate": 1.1594294670388265}, {"bootstrap": 1, "max_depth": 19, "max_features": 0.8, "min_samples_leaf": 8, "n_estimators": 1, "score": 0.6388049450549451, "surrogate": 0.9312499090319406}, {"bootstrap": 0, "max_depth": 8, "max_features": 1.0, "min_samples_leaf": 9, "n_estimators": 1942, "score": 0.8768666056166057, "surrogate": 0.6810440967635181}, {"bootstrap": 0, "max_depth": 19, "max_features": 0.6, "min_samples_leaf": 9, "n_estimators": 136, "score": 0.9146886446886449, "surrogate": 1.2000603931377123}, {"bootstrap": 0, "max_depth": 7, "max_features": 0.8, "min_samples_leaf": 9, "n_estimators": 1952, "score": 0.9076709401709401, "surrogate": 0.8735928791343328}, {"bootstrap": 1, "max_depth": 5, "max_features": 0.9, "min_samples_leaf": 1, "n_estimators": 1942, "score": 0.87497557997558, "surrogate": 0.7881357299863412}, {"bootstrap": 1, "max_depth": 19, "max_features": 0.8, "min_samples_leaf": 1, "n_estimators": 1908, "score": 0.9914636752136751, "surrogate": 0.9427937300881517}, {"bootstrap": 1, "max_depth": 9, "max_features": 0.6, "min_samples_leaf": 9, "n_estimators": 1976, "score": 0.8412393162393161, "surrogate": 0.8998733211829375}, {"bootstrap": 1, "max_depth": 19, "max_features": 0.6, "min_samples_leaf": 1, "n_estimators": 1828, "score": 0.98252442002442, "surrogate": 0.9159579988113684}, {"bootstrap": 1, "max_depth": 19, "max_features": "sqrt", "min_samples_leaf": 4, "n_estimators": 1958, "score": 0.9039285714285714, "surrogate": 1.0285904198515854}, {"bootstrap": 0, "max_depth": 7, "max_features": 0.9, "min_samples_leaf": 1, "n_estimators": 18, "score": 0.99875, "surrogate": 0.8910278532161122}, {"bootstrap": 0, "max_depth": 19, "max_features": 0.6, "min_samples_leaf": 8, "n_estimators": 1982, "score": 0.9297802197802199, "surrogate": 1.0147604021224872}, {"bootstrap": 1, "max_depth": 10, "max_features": 0.8, "min_samples_leaf": 1, "n_estimators": 1944, "score": 0.9925412087912088, "surrogate": 1.0019703331997083}, {"bootstrap": 0, "max_depth": 17, "max_features": 0.7, "min_samples_leaf": 1, "n_estimators": 12, "score": 0.9979532967032967, "surrogate": 0.9756909872485924}, {"bootstrap": 1, "max_depth": 17, "max_features": 1.0, "min_samples_leaf": 1, "n_estimators": 1992, "score": 0.9958333333333333, "surrogate": 1.0961587162013338}, {"bootstrap": 0, "max_depth": 19, "max_features": 0.8, "min_samples_leaf": 1, "n_estimators": 1945, "score": 0.9982142857142857, "surrogate": 1.0233321380615443}, {"bootstrap": 0, "max_depth": 17, "max_features": 0.1, "min_samples_leaf": 1, "n_estimators": 668, "score": 0.9789911477411477, "surrogate": 0.9886017144078956}, {"bootstrap": 1, "max_depth": 8, "max_features": 1.0, "min_samples_leaf": 1, "n_estimators": 925, "score": 0.9955952380952381, "surrogate": 0.9703100786363069}, {"bootstrap": 1, "max_depth": 11, "max_features": 0.8, "min_samples_leaf": 1, "n_estimators": 75, "score": 0.9931410256410256, "surrogate": 0.919714213817235}, {"bootstrap": 0, "max_depth": 8, "max_features": 0.8, "min_samples_leaf": 9, "n_estimators": 6, "score": 0.8807829670329671, "surrogate": 0.7696606582441348}, {"bootstrap": 0, "max_depth": 3, "max_features": 0.8, "min_samples_leaf": 7, "n_estimators": 1866, "score": 0.7399816849816849, "surrogate": 0.6231126772116387}, {"bootstrap": 0, "max_depth": 16, "max_features": 0.8, "min_samples_leaf": 1, "n_estimators": 1996, "score": 0.9982142857142857, "surrogate": 1.0746669062647767}, {"bootstrap": 0, "max_depth": 11, "max_features": 0.3, "min_samples_leaf": 1, "n_estimators": 1951, "score": 0.9789590964590964, "surrogate": 1.0634326852158935}, {"bootstrap": 1, "max_depth": 14, "max_features": 0.6, "min_samples_leaf": 1, "n_estimators": 1989, "score": 0.9831532356532356, "surrogate": 1.0563465980580098}, {"bootstrap": 0, "max_depth": 19, "max_features": 0.2, "min_samples_leaf": 9, "n_estimators": 1951, "score": 0.8992887667887668, "surrogate": 0.8787059368533789}, {"bootstrap": 0, "max_depth": 9, "max_features": 0.6, "min_samples_leaf": 1, "n_estimators": 140, "score": 0.9978571428571428, "surrogate": 1.005137105021694}], [{"n_estimators": 491, "min_samples_leaf": 7, "max_features": 0.2, "max_depth": 4, "bootstrap": false, "score": 0.8551434676434676, "surrogate": 0.8551434676434676}, {"bootstrap": 0, "max_depth": 5, "max_features": 0.2, "min_samples_leaf": 4, "n_estimators": 1348, "score": 0.910625763125763, "surrogate": 0.1382914471486969}, {"bootstrap": 0, "max_depth": 19, "max_features": "log2", "min_samples_leaf": 2, "n_estimators": 1998, "score": 0.9803846153846154, "surrogate": 0.05458573923913679}, {"bootstrap": 1, "max_depth": 18, "max_features": 0.8, "min_samples_leaf": 5, "n_estimators": 1534, "score": 0.9122710622710624, "surrogate": 0.0}, {"bootstrap": 0, "max_depth": 19, "max_features": 0.4, "min_samples_leaf": 1, "n_estimators": 89, "score": 0.9901327838827839, "surrogate": 0.01043276165700957}, {"bootstrap": 0, "max_depth": 19, "max_features": 0.3, "min_samples_leaf": 1, "n_estimators": 1487, "score": 0.9803327228327229, "surrogate": 0.009112142284944502}, {"bootstrap": 1, "max_depth": 19, "max_features": 0.9, "min_samples_leaf": 1, "n_estimators": 79, "score": 0.995534188034188, "surrogate": 0.009094172738662865}, {"bootstrap": 0, "max_depth": 19, "max_features": 0.7, "min_samples_leaf": 9, "n_estimators": 1965, "score": 0.907554945054945, "surrogate": 0.007780383463867557}, {"bootstrap": 0, "max_depth": 19, "max_features": 0.6, "min_samples_leaf": 8, "n_estimators": 1970, "score": 0.9326709401709401, "surrogate": 0.00738852840833501}, {"bootstrap": 0, "max_depth": 19, "max_features": 1.0, "min_samples_leaf": 9, "n_estimators": 1959, "score": 0.8772237484737484, "surrogate": 0.007220155945095452}, {"bootstrap": 1, "max_depth": 6, "max_features": 0.1, "min_samples_leaf": 4, "n_estimators": 1995, "score": 0.8891941391941393, "surrogate": 0.011967263656780469}, {"bootstrap": 1, "max_depth": 9, "max_features": 0.4, "min_samples_leaf": 9, "n_estimators": 1213, "score": 0.8322008547008547, "surrogate": 0.0}, {"bootstrap": 1, "max_depth": 19, "max_features": "sqrt", "min_samples_leaf": 1, "n_estimators": 175, "score": 0.9682020757020757, "surrogate": 0.009285291863035172}, {"bootstrap": 0, "max_depth": 18, "max_features": 0.5, "min_samples_leaf": 1, "n_estimators": 1883, "score": 0.9979761904761905, "surrogate": 0.013679865905758037}, {"bootstrap": 1, "max_depth": 19, "max_features": 0.2, "min_samples_leaf": 1, "n_estimators": 1803, "score": 0.9527442002442003, "surrogate": 1.0168206623137905}, {"bootstrap": 0, "max_depth": 14, "max_features": 1.0, "min_samples_leaf": 9, "n_estimators": 1811, "score": 0.8771047008547008, "surrogate": 0.771314571684254}, {"bootstrap": 1, "max_depth": 18, "max_features": 0.7, "min_samples_leaf": 1, "n_estimators": 1999, "score": 0.993264652014652, "surrogate": 1.0627189931039993}, {"bootstrap": 0, "max_depth": 9, "max_features": 0.6, "min_samples_leaf": 1, "n_estimators": 1994, "score": 0.9979761904761905, "surrogate": 1.0268860576602847}, {"bootstrap": 0, "max_depth": 19, "max_features": 1.0, "min_samples_leaf": 1, "n_estimators": 1408, "score": 0.9672115384615385, "surrogate": 0.965355109835814}, {"bootstrap": 1, "max_depth": 19, "max_features": 0.5, "min_samples_leaf": 3, "n_estimators": 1703, "score": 0.9425763125763126, "surrogate": 0.9850392078045616}, {"bootstrap": 0, "max_depth": 1, "max_features": 0.7, "min_samples_leaf": 1, "n_estimators": 1982, "score": 0.5340155677655678, "surrogate": 0.952230948918583}, {"bootstrap": 0, "max_depth": 19, "max_features": 0.7, "min_samples_leaf": 1, "n_estimators": 1994, "score": 0.9982142857142857, "surrogate": 1.0277716641884407}, {"bootstrap": 0, "max_depth": 11, "max_features": 0.9, "min_samples_leaf": 4, "n_estimators": 296, "score": 0.9832600732600734, "surrogate": 1.0634901948254871}, {"bootstrap": 0, "max_depth": 1, "max_features": 0.9, "min_samples_leaf": 1, "n_estimators": 1930, "score": 0.5152228327228328, "surrogate": 0.9559168713824562}, {"bootstrap": 0, "max_depth": 18, "max_features": 0.1, "min_samples_leaf": 1, "n_estimators": 1881, "score": 0.9801373626373626, "surrogate": 1.067905123345085}, {"bootstrap": 0, "max_depth": 14, "max_features": 0.6, "min_samples_leaf": 1, "n_estimators": 127, "score": 0.9964804639804641, "surrogate": 1.0628250889013273}, {"bootstrap": 0, "max_depth": 7, "max_features": 0.9, "min_samples_leaf": 9, "n_estimators": 172, "score": 0.8971031746031747, "surrogate": 0.9430282209203185}, {"bootstrap": 0, "max_depth": 8, "max_features": 0.5, "min_samples_leaf": 1, "n_estimators": 1922, "score": 0.9980952380952381, "surrogate": 1.0176924620798786}, {"bootstrap": 0, "max_depth": 8, "max_features": "log2", "min_samples_leaf": 1, "n_estimators": 42, "score": 0.9938034188034187, "surrogate": 1.0251391901137654}, {"bootstrap": 0, "max_depth": 16, "max_features": 0.9, "min_samples_leaf": 1, "n_estimators": 46, "score": 0.9964652014652013, "surrogate": 1.0258069967255778}, {"bootstrap": 1, "max_depth": 12, "max_features": 0.9, "min_samples_leaf": 1, "n_estimators": 1862, "score": 0.9955952380952381, "surrogate": 0.9824463240094161}, {"bootstrap": 0, "max_depth": 12, "max_features": 0.4, "min_samples_leaf": 1, "n_estimators": 1854, "score": 0.9916147741147741, "surrogate": 0.9709091288856673}, {"bootstrap": 0, "max_depth": 7, "max_features": 0.8, "min_samples_leaf": 1, "n_estimators": 1959, "score": 0.9982142857142857, "surrogate": 0.9742220614750181}, {"bootstrap": 0, "max_depth": 11, "max_features": 0.8, "min_samples_leaf": 1, "n_estimators": 1892, "score": 0.9983333333333334, "surrogate": 1.0109870862888783}, {"bootstrap": 1, "max_depth": 16, "max_features": 0.9, "min_samples_leaf": 9, "n_estimators": 1558, "score": 0.8365079365079364, "surrogate": 1.0833956749010625}, {"bootstrap": 0, "max_depth": 1, "max_features": 1.0, "min_samples_leaf": 9, "n_estimators": 1523, "score": 0.5101739926739927, "surrogate": 0.7464459123756217}, {"bootstrap": 1, "max_depth": 8, "max_features": 0.9, "min_samples_leaf": 1, "n_estimators": 1906, "score": 0.9949999999999999, "surrogate": 0.959644744698938}, {"bootstrap": 0, "max_depth": 7, "max_features": 1.0, "min_samples_leaf": 1, "n_estimators": 1860, "score": 0.9641575091575092, "surrogate": 1.003554296070888}, {"bootstrap": 0, "max_depth": 5, "max_features": "sqrt", "min_samples_leaf": 1, "n_estimators": 1903, "score": 0.9336019536019535, "surrogate": 0.9231924589217329}, {"bootstrap": 1, "max_depth": 15, "max_features": 0.6, "min_samples_leaf": 1, "n_estimators": 1828, "score": 0.9840888278388278, "surrogate": 0.9824103717504187}, {"bootstrap": 1, "max_depth": 10, "max_features": 0.7, "min_samples_leaf": 1, "n_estimators": 19, "score": 0.9875106837606837, "surrogate": 0.9896216457822358}, {"bootstrap": 0, "max_depth": 13, "max_features": 0.5, "min_samples_leaf": 1, "n_estimators": 65, "score": 0.9970833333333333, "surrogate": 1.0375574835793984}, {"bootstrap": 1, "max_depth": 1, "max_features": 0.2, "min_samples_leaf": 1, "n_estimators": 167, "score": 0.542542735042735, "surrogate": 0.7579528804685811}, {"bootstrap": 0, "max_depth": 9, "max_features": 0.9, "min_samples_leaf": 1, "n_estimators": 1966, "score": 0.9967994505494506, "surrogate": 1.009391919385024}, {"bootstrap": 0, "max_depth": 10, "max_features": 0.2, "min_samples_leaf": 7, "n_estimators": 1983, "score": 0.9113186813186811, "surrogate": 0.9545313635535422}, {"bootstrap": 1, "max_depth": 14, "max_features": 0.2, "min_samples_leaf": 5, "n_estimators": 35, "score": 0.8671886446886446, "surrogate": 0.9615928504020559}, {"bootstrap": 0, "max_depth": 7, "max_features": 1.0, "min_samples_leaf": 7, "n_estimators": 2, "score": 0.8895512820512821, "surrogate": 0.9834433457232805}, {"bootstrap": 1, "max_depth": 8, "max_features": 0.2, "min_samples_leaf": 1, "n_estimators": 1946, "score": 0.9542948717948718, "surrogate": 0.9748411413322984}, {"bootstrap": 0, "max_depth": 5, "max_features": 0.4, "min_samples_leaf": 1, "n_estimators": 103, "score": 0.9354975579975578, "surrogate": 0.8979770517968859}, {"bootstrap": 1, "max_depth": 1, "max_features": 0.3, "min_samples_leaf": 9, "n_estimators": 384, "score": 0.533391330891331, "surrogate": 0.6394253455063114}, {"bootstrap": 0, "max_depth": 19, "max_features": 0.9, "min_samples_leaf": 1, "n_estimators": 1568, "score": 0.9959065934065935, "surrogate": 1.0119138900236457}], [{"n_estimators": 969, "min_samples_leaf": 2, "max_features": 0.3, "max_depth": 14, "bootstrap": false, "score": 0.9679975579975579, "surrogate": 0.9679975579975579}, {"bootstrap": 0, "max_depth": 15, "max_features": 0.3, "min_samples_leaf": 5, "n_estimators": 169, "score": 0.9308730158730159, "surrogate": 0.17655175213717875}, {"bootstrap": 0, "max_depth": 1, "max_features": "log2", "min_samples_leaf": 2, "n_estimators": 1903, "score": 0.5463156288156288, "surrogate": 0.05987781755689281}, {"bootstrap": 1, "max_depth": 17, "max_features": 0.7, "min_samples_leaf": 7, "n_estimators": 1470, "score": 0.8697069597069597, "surrogate": 0.0}, {"bootstrap": 1, "max_depth": 1, "max_features": "sqrt", "min_samples_leaf": 1, "n_estimators": 1781, "score": 0.5469627594627595, "surrogate": 0.009272931521078553}, {"bootstrap": 1, "max_depth": 19, "max_features": 1.0, "min_samples_leaf": 1, "n_estimators": 439, "score": 0.9962500000000001, "surrogate": 0.008305261311901901}, {"bootstrap": 1, "max_depth": 19, "max_features": 0.4, "min_samples_leaf": 1, "n_estimators": 130, "score": 0.9651236263736264, "surrogate": 0.008640348965013943}, {"bootstrap": 0, "max_depth": 3, "max_features": 0.2, "min_samples_leaf": 1, "n_estimators": 82, "score": 0.7794322344322344, "surrogate": 0.006484678188474202}, {"bootstrap": 1, "max_depth": 19, "max_features": 0.5, "min_samples_leaf": 1, "n_estimators": 514, "score": 0.9834645909645909, "surrogate": 0.011368678439918276}, {"bootstrap": 0, "max_depth": 19, "max_features": 0.8, "min_samples_leaf": 2, "n_estimators": 13, "score": 0.9936309523809523, "surrogate": 0.004264053597821282}, {"bootstrap": 0, "max_depth": 19, "max_features": 0.9, "min_samples_leaf": 4, "n_estimators": 1, "score": 0.9417689255189254, "surrogate": 0.004912460521343726}, {"bootstrap": 1, "max_depth": 1, "max_features": 0.6, "min_samples_leaf": 1, "n_estimators": 1843, "score": 0.5442918192918192, "surrogate": 0.006813247265749389}, {"bootstrap": 0, "max_depth": 2, "max_features": 0.1, "min_samples_leaf": 1, "n_estimators": 3, "score": 0.6129166666666667, "surrogate": 0.0061239707122509625}, {"bootstrap": 1, "max_depth": 19, "max_features": 0.1, "min_samples_leaf": 9, "n_estimators": 1671, "score": 0.8364713064713065, "surrogate": 0.5438389708553645}, {"bootstrap": 0, "max_depth": 19, "max_features": 0.6, "min_samples_leaf": 1, "n_estimators": 1977, "score": 0.9979761904761905, "surrogate": 0.8307679235679233}, {"bootstrap": 0, "max_depth": 8, "max_features": 0.9, "min_samples_leaf": 9, "n_estimators": 1857, "score": 0.8922405372405372, "surrogate": 1.0383152590892486}, {"bootstrap": 1, "max_depth": 19, "max_features": "log2", "min_samples_leaf": 3, "n_estimators": 10, "score": 0.89242673992674, "surrogate": 0.7206834213443472}, {"bootstrap": 0, "max_depth": 19, "max_features": 0.2, "min_samples_leaf": 1, "n_estimators": 27, "score": 0.9788110500610501, "surrogate": 1.073292033574404}, {"bootstrap": 1, "max_depth": 11, "max_features": 0.1, "min_samples_leaf": 1, "n_estimators": 44, "score": 0.9486828449328449, "surrogate": 0.8882849055549116}, {"bootstrap": 0, "max_depth": 9, "max_features": 0.8, "min_samples_leaf": 1, "n_estimators": 132, "score": 0.9984523809523809, "surrogate": 1.041103655425676}, {"bootstrap": 0, "max_depth": 19, "max_features": "log2", "min_samples_leaf": 1, "n_estimators": 1855, "score": 0.9914392551892552, "surrogate": 0.892954244753291}, {"bootstrap": 0, "max_depth": 10, "max_features": 1.0, "min_samples_leaf": 1, "n_estimators": 84, "score": 0.9672115384615385, "surrogate": 1.0755926921123802}, {"bootstrap": 1, "max_depth": 4, "max_features": 0.8, "min_samples_leaf": 9, "n_estimators": 6, "score": 0.7096810134310134, "surrogate": 0.833799621043152}, {"bootstrap": 0, "max_depth": 11, "max_features": 0.2, "min_samples_leaf": 9, "n_estimators": 1982, "score": 0.8927655677655679, "surrogate": 0.9690819440192584}, {"bootstrap": 0, "max_depth": 13, "max_features": 0.8, "min_samples_leaf": 9, "n_estimators": 155, "score": 0.9055555555555556, "surrogate": 0.9622739976356822}, {"bootstrap": 0, "max_depth": 17, "max_features": 0.7, "min_samples_leaf": 1, "n_estimators": 1790, "score": 0.9982142857142857, "surrogate": 0.9935823338061347}, {"bootstrap": 0, "max_depth": 10, "max_features": 0.2, "min_samples_leaf": 1, "n_estimators": 1641, "score": 0.9794887057387058, "surrogate": 1.0005543364370197}, {"bootstrap": 1, "max_depth": 7, "max_features": 0.9, "min_samples_leaf": 1, "n_estimators": 1996, "score": 0.9949999999999999, "surrogate": 1.0246530612524225}, {"bootstrap": 0, "max_depth": 19, "max_features": 0.1, "min_samples_leaf": 1, "n_estimators": 1490, "score": 0.9800152625152625, "surrogate": 1.0216806430790726}, {"bootstrap": 1, "max_depth": 8, "max_features": 0.8, "min_samples_leaf": 5, "n_estimators": 1912, "score": 0.9126892551892553, "surrogate": 0.9808025336408797}, {"bootstrap": 0, "max_depth": 14, "max_features": 0.9, "min_samples_leaf": 1, "n_estimators": 29, "score": 0.995728021978022, "surrogate": 1.0576527529388677}, {"bootstrap": 0, "max_depth": 10, "max_features": "log2", "min_samples_leaf": 1, "n_estimators": 1861, "score": 0.9916147741147741, "surrogate": 0.9781964717636704}, {"bootstrap": 0, "max_depth": 9, "max_features": "log2", "min_samples_leaf": 9, "n_estimators": 1973, "score": 0.9078144078144078, "surrogate": 0.8213320460170053}, {"bootstrap": 0, "max_depth": 7, "max_features": 0.7, "min_samples_leaf": 1, "n_estimators": 48, "score": 1.0, "surrogate": 0.9875436247028517}, {"bootstrap": 0, "max_depth": 7, "max_features": 0.5, "min_samples_leaf": 1, "n_estimators": 1576, "score": 0.9974999999999999, "surrogate": 1.024897414278719}, {"bootstrap": 0, "max_depth": 15, "max_features": "log2", "min_samples_leaf": 1, "n_estimators": 41, "score": 0.9873199023199023, "surrogate": 1.0045604325102033}, {"bootstrap": 1, "max_depth": 17, "max_features": 0.8, "min_samples_leaf": 1, "n_estimators": 1890, "score": 0.9922527472527474, "surrogate": 1.0432092054089992}, {"bootstrap": 1, "max_depth": 7, "max_features": 0.4, "min_samples_leaf": 1, "n_estimators": 100, "score": 0.9616483516483516, "surrogate": 0.9636935184954041}, {"bootstrap": 0, "max_depth": 7, "max_features": "log2", "min_samples_leaf": 1, "n_estimators": 183, "score": 0.9902075702075702, "surrogate": 0.9929464146798566}, {"bootstrap": 1, "max_depth": 10, "max_features": 1.0, "min_samples_leaf": 6, "n_estimators": 98, "score": 0.8901221001221001, "surrogate": 1.0413372018399913e-29}, {"bootstrap": 0, "max_depth": 16, "max_features": 0.2, "min_samples_leaf": 8, "n_estimators": 1812, "score": 0.911965811965812, "surrogate": 0.0}, {"bootstrap": 0, "max_depth": 19, "max_features": 1.0, "min_samples_leaf": 9, "n_estimators": 180, "score": 0.8774618437118438, "surrogate": 0.9512232538664023}, {"bootstrap": 1, "max_depth": 9, "max_features": "log2", "min_samples_leaf": 1, "n_estimators": 1891, "score": 0.9683211233211233, "surrogate": 0.9676901559261744}, {"bootstrap": 0, "max_depth": 19, "max_features": "sqrt", "min_samples_leaf": 9, "n_estimators": 92, "score": 0.9112881562881563, "surrogate": 0.2823442922605252}, {"bootstrap": 1, "max_depth": 1, "max_features": 0.1, "min_samples_leaf": 4, "n_estimators": 1944, "score": 0.5510286935286935, "surrogate": 0.5371954775289812}, {"bootstrap": 0, "max_depth": 11, "max_features": "sqrt", "min_samples_leaf": 1, "n_estimators": 120, "score": 0.9903174603174604, "surrogate": 1.0021843099109873}, {"bootstrap": 1, "max_depth": 8, "max_features": 0.3, "min_samples_leaf": 1, "n_estimators": 45, "score": 0.94751221001221, "surrogate": 0.9865045943389451}, {"bootstrap": 0, "max_depth": 6, "max_features": 1.0, "min_samples_leaf": 5, "n_estimators": 1859, "score": 0.9374160561660562, "surrogate": 0.8843554354706242}, {"bootstrap": 1, "max_depth": 14, "max_features": 0.9, "min_samples_leaf": 1, "n_estimators": 1596, "score": 0.9955952380952381, "surrogate": 1.0001507292072347}, {"bootstrap": 1, "max_depth": 19, "max_features": 0.9, "min_samples_leaf": 1, "n_estimators": 1946, "score": 0.9954761904761906, "surrogate": 0.9986316211847535}, {"bootstrap": 0, "max_depth": 1, "max_features": 0.9, "min_samples_leaf": 9, "n_estimators": 269, "score": 0.5152228327228328, "surrogate": 0.5871803461709426}]], "scores": [0.9413542938542938, 0.9646072446072447, 0.9646072446072447, 0.9678566341066341, 0.9947069597069597, 0.9965074277574278, 0.9965074277574278, 0.9965074277574278, 0.9965074277574278, 0.9965074277574278, 0.9965074277574278, 0.9965074277574278, 0.9973214285714286, 0.9978968253968254, 0.9978968253968254, 0.9978968253968254, 0.9978968253968254, 0.9978968253968254, 0.9980555555555556, 0.9980555555555556, 0.9981349206349206, 0.9981349206349206, 0.9981349206349206, 0.9981349206349206, 0.9981349206349206, 0.9981349206349206, 0.9981349206349206, 0.9981349206349206, 0.9981349206349206, 0.9981349206349206, 0.9981349206349206, 0.9981349206349206, 0.9986904761904762, 0.9986904761904762, 0.9990277777777777, 0.9990277777777777, 0.9990277777777777, 0.9990277777777777, 0.9990277777777777, 0.9990277777777777, 0.9990277777777777, 0.9990277777777777, 0.9990277777777777, 0.9990277777777777, 0.9990277777777777, 0.9990277777777777, 0.9990277777777777, 0.9990277777777777, 0.9990277777777777, 0.9990277777777777]}